libopenzwave.cp36-win32.pyd
openzwave/__init__.py
openzwave/command.py
openzwave/controller.py
openzwave/group.py
openzwave/network.py
openzwave/node.py
openzwave/object.py
openzwave/option.py
openzwave/scene.py
openzwave/singleton.py
openzwave/value.py
pyozwman/__init__.py
pyozwman/ozwsh_main.py
pyozwman/ozwsh_widgets.py
python_openzwave/__init__.py
python_openzwave/ozw_config/__init__.py
python_openzwave/ozw_config/device_classes.xml
python_openzwave/ozw_config/device_classes.xsd
python_openzwave/ozw_config/device_configuration.xsd
python_openzwave/ozw_config/manufacturer_specific.xml
python_openzwave/ozw_config/manufacturer_specific.xsd
python_openzwave/ozw_config/options.xml
python_openzwave/ozw_config/options.xsd
python_openzwave/ozw_config/zwcfg.xsd
python_openzwave/ozw_config/zwscene.xsd
python_openzwave/ozw_config/2gig/ct100.xml
python_openzwave/ozw_config/2gig/ct101.xml
python_openzwave/ozw_config/2gig/ct30.xml
python_openzwave/ozw_config/2gig/ct32.xml
python_openzwave/ozw_config/2gig/ct50e.xml
python_openzwave/ozw_config/2gig/ct80.xml
python_openzwave/ozw_config/BeNext/1poleswitch.xml
python_openzwave/ozw_config/BeNext/2poleswitch.xml
python_openzwave/ozw_config/BeNext/AlarmSound.xml
python_openzwave/ozw_config/BeNext/BuiltinDimmer.xml
python_openzwave/ozw_config/BeNext/DoorSensor.xml
python_openzwave/ozw_config/BeNext/EnergySwitch.xml
python_openzwave/ozw_config/BeNext/HeatingControl.xml
python_openzwave/ozw_config/BeNext/Molite.xml
python_openzwave/ozw_config/BeNext/P1dongle.xml
python_openzwave/ozw_config/BeNext/PanicButton.xml
python_openzwave/ozw_config/BeNext/PanicWatch.xml
python_openzwave/ozw_config/BeNext/PluginDimmer.xml
python_openzwave/ozw_config/BeNext/SceneController.xml
python_openzwave/ozw_config/BeNext/TagReader.xml
python_openzwave/ozw_config/BeNext/TagReader500.xml
python_openzwave/ozw_config/act/lfm20.xml
python_openzwave/ozw_config/act/zdm230.xml
python_openzwave/ozw_config/act/zdw103.xml
python_openzwave/ozw_config/act/zdw232.xml
python_openzwave-0.4.19.dist-info/LICENSE.txt
python_openzwave-0.4.19.dist-info/METADATA
python_openzwave-0.4.19.dist-info/WHEEL
python_openzwave-0.4.19.dist-info/entry_points.txt
python_openzwave-0.4.19.dist-info/top_level.txt
python_openzwave-0.4.19.dist-info/RECORD
